analysis_package/__init__.py
analysts_task_pkg_macca2707-0.0.1.dist-info/LICENSE
analysts_task_pkg_macca2707-0.0.1.dist-info/METADATA
analysts_task_pkg_macca2707-0.0.1.dist-info/WHEEL
analysts_task_pkg_macca2707-0.0.1.dist-info/top_level.txt
analysts_task_pkg_macca2707-0.0.1.dist-info/RECORD
